toga_cassowary/__init__.py
toga_cassowary/layout.py
toga_cassowary/widget.py
toga_cassowary-0.1.2.dist-info/DESCRIPTION.rst
toga_cassowary-0.1.2.dist-info/METADATA
toga_cassowary-0.1.2.dist-info/metadata.json
toga_cassowary-0.1.2.dist-info/RECORD
toga_cassowary-0.1.2.dist-info/top_level.txt
toga_cassowary-0.1.2.dist-info/WHEEL
